setup.py
aimvv_app1/__init__.py
aimvv_app1/module_one.py
aimvv_app1/module_two.py
aimvv_app1.egg-info/PKG-INFO
aimvv_app1.egg-info/SOURCES.txt
aimvv_app1.egg-info/dependency_links.txt
aimvv_app1.egg-info/top_level.txt