Metadata-Version: 2.1
Name: aimvv-app1
Version: 0.0.1
Summary: My Package
Author: test
Author-email: vldmsnl@yandex.ru
